AUTHORS.rst
CHANGES.rst
LICENSE.txt
MANIFEST.in
README.rst
setup.cfg
setup.py
birdhousebuilder/__init__.py
birdhousebuilder.recipe.sphinx.egg-info/PKG-INFO
birdhousebuilder.recipe.sphinx.egg-info/SOURCES.txt
birdhousebuilder.recipe.sphinx.egg-info/dependency_links.txt
birdhousebuilder.recipe.sphinx.egg-info/entry_points.txt
birdhousebuilder.recipe.sphinx.egg-info/namespace_packages.txt
birdhousebuilder.recipe.sphinx.egg-info/not-zip-safe
birdhousebuilder.recipe.sphinx.egg-info/requires.txt
birdhousebuilder.recipe.sphinx.egg-info/top_level.txt
birdhousebuilder/recipe/__init__.py
birdhousebuilder/recipe/sphinx/Makefile
birdhousebuilder/recipe/sphinx/README.txt
birdhousebuilder/recipe/sphinx/__init__.py
birdhousebuilder/recipe/sphinx/conf_py
birdhousebuilder/recipe/sphinx/index.rst
birdhousebuilder/recipe/sphinx/rtd.txt
birdhousebuilder/recipe/sphinx/tests/__init__.py
birdhousebuilder/recipe/sphinx/tests/test_doctests.py