Metadata-Version: 1.1
Name: birdhousebuilder.recipe.sphinx
Version: 0.2.4
Summary: Buildout recipe to generate and Sphinx-based documentation for Birdhouse.
Home-page: https://github.com/birdhouse/birdhousebuilder.recipe.sphinx
Author: Birdhouse
Author-email: wps-dev@dkrz.de
License: Apache License 2.0
Keywords: buildout sphinx birdhouse
Platform: UNKNOWN
Classifier: Framework :: Buildout
Classifier: Intended Audience :: Developers
Classifier: Programming Language :: Python :: 2
Classifier: Topic :: Software Development :: Build Tools
Classifier: Topic :: Software Development :: Libraries :: Python Modules
Classifier: Topic :: Scientific/Engineering :: Atmospheric Science
